LICENSE.txt
mmlspark/__init__.py
mmlspark/automl/FindBestModel.py
mmlspark/automl/HyperparamBuilder.py
mmlspark/automl/TuneHyperparameters.py
mmlspark/automl/__init__.py
mmlspark/cntk/CNTKModel.py
mmlspark/cntk/__init__.py
mmlspark/cognitive/AzureSearchWriter.py
mmlspark/cognitive/BingImageSearch.py
mmlspark/cognitive/__init__.py
mmlspark/core/__init__.py
mmlspark/core/schema/TypeConversionUtils.py
mmlspark/core/schema/Utils.py
mmlspark/core/schema/__init__.py
mmlspark/core/serialize/__init__.py
mmlspark/core/serialize/java_params_patch.py
mmlspark/core/spark/FluentAPI.py
mmlspark/core/spark/__init__.py
mmlspark/cyber/__init__.py
mmlspark/cyber/dataset.py
mmlspark/cyber/anomaly/__init__.py
mmlspark/cyber/anomaly/collaborative_filtering.py
mmlspark/cyber/anomaly/complement_access.py
mmlspark/cyber/feature/__init__.py
mmlspark/cyber/feature/indexers.py
mmlspark/cyber/feature/scalers.py
mmlspark/cyber/utils/__init__.py
mmlspark/cyber/utils/spark_utils.py
mmlspark/downloader/ModelDownloader.py
mmlspark/downloader/__init__.py
mmlspark/image/ImageFeaturizer.py
mmlspark/image/__init__.py
mmlspark/io/IOImplicits.py
mmlspark/io/__init__.py
mmlspark/io/binary/BinaryFileReader.py
mmlspark/io/binary/__init__.py
mmlspark/io/http/HTTPFunctions.py
mmlspark/io/http/JSONOutputParser.py
mmlspark/io/http/ServingFunctions.py
mmlspark/io/http/SimpleHTTPTransformer.py
mmlspark/io/http/__init__.py
mmlspark/io/image/ImageUtils.py
mmlspark/io/image/__init__.py
mmlspark/io/powerbi/PowerBIWriter.py
mmlspark/io/powerbi/__init__.py
mmlspark/lightgbm/LightGBMClassifier.py
mmlspark/lightgbm/LightGBMRanker.py
mmlspark/lightgbm/LightGBMRegressor.py
mmlspark/lightgbm/__init__.py
mmlspark/nn/ConditionalBallTree.py
mmlspark/nn/__init__.py
mmlspark/opencv/ImageTransformer.py
mmlspark/opencv/__init__.py
mmlspark/plot/__init__.py
mmlspark/plot/plot.py
mmlspark/recommendation/RankingTrainValidationSplit.py
mmlspark/recommendation/RankingTrainValidationSplitModel.py
mmlspark/recommendation/SAR.py
nozberkman_mmlspark-1.0.0.dist-info/LICENSE.txt
nozberkman_mmlspark-1.0.0.dist-info/METADATA
nozberkman_mmlspark-1.0.0.dist-info/WHEEL
nozberkman_mmlspark-1.0.0.dist-info/top_level.txt
nozberkman_mmlspark-1.0.0.dist-info/zip-safe
nozberkman_mmlspark-1.0.0.dist-info/RECORD
